[
  {
    "id": 100,
    "CardType": 0,
    "CardName_zh": "刻晴",
    "CardName": "Keqing",
    "CardInfo": "My Waifu",
    "HP": 12,
    "ATK": 5,
    "ATKElement": 0,
    "SelfElement": 0,
    "Charge": 3
  },
  {
    "id": 101,
    "CardType": 0,
    "CardName_zh": "胡桃",
    "CardName": "Hutao",
    "CardInfo": "My Waifu",
    "HP": 10,
    "ATK": 6,
    "ATKElement": 0,
    "SelfElement": 0,
    "Charge": 3
  },
  {
    "id": 200,
    "CardType": 1,
    "CardName_zh": "丘丘人",
    "CardName": "Hilichurl",
    "CardInfo": "Your Wife",
    "HP": 11,
    "ATK": 3,
    "ATKElement": 0,
    "SelfElement": 0,
    "Charge": 0
  },
  {
    "id": 201,
    "CardType": 1,
    "CardName_zh": "打手丘丘人",
    "CardName": "Hilichurl Fighter",
    "CardInfo": "Your Wife",
    "HP": 7,
    "ATK": 5,
    "ATKElement": 0,
    "SelfElement": 0,
    "Charge": 0
  },
  {
    "id": 202,
    "CardType": 1,
    "CardName_zh": "史莱姆·水",
    "CardName": "Hydro Slime",
    "CardInfo": "Your Wife",
    "HP": 11,
    "ATK": 2,
    "ATKElement": 1,
    "SelfElement": 1,
    "Charge": 0
  },
  {
    "id": 203,
    "CardType": 1,
    "CardName_zh": "史莱姆·火",
    "CardName": "Pyro Slime",
    "CardInfo": "Your Wife",
    "HP": 7,
    "ATK": 5,
    "ATKElement": 2,
    "SelfElement": 2,
    "Charge": 0
  },
  {
    "id": 204,
    "CardType": 1,
    "CardName_zh": "史莱姆·冰",
    "CardName": "Cryo Slime",
    "CardInfo": "Your Wife",
    "HP": 8,
    "ATK": 4,
    "ATKElement": 3,
    "SelfElement": 3,
    "Charge": 0
  },
  {
    "id": 205,
    "CardType": 1,
    "CardName_zh": "史莱姆·雷",
    "CardName": "Electro Slime",
    "CardInfo": "Your Wife",
    "HP": 8,
    "ATK": 4,
    "ATKElement": 4,
    "SelfElement": 4,
    "Charge": 0
  },
  {
    "id": 206,
    "CardType": 1,
    "CardName_zh": "史莱姆·岩",
    "CardName": "Geo Slime",
    "CardInfo": "Your Wife",
    "HP": 8,
    "ATK": 2,
    "ATKElement": 5,
    "SelfElement": 0,
    "Charge": 0
  },
  {
    "id": 207,
    "CardType": 1,
    "CardName_zh": "史莱姆·风",
    "CardName": "Anemo Slime",
    "CardInfo": "Your Wife",
    "HP": 8,
    "ATK": 2,
    "ATKElement": 6,
    "SelfElement": 0,
    "Charge": 0
  },
  {
    "id": 300,
    "CardType": 2,
    "CardName_zh": "霜铠丘丘王",
    "CardName": "FrostarmLawachurl",
    "CardInfo": "Your Father",
    "HP": 100,
    "ATK": 0,
    "ATKElement": 0,
    "SelfElement": 0,
    "Charge": 3
  }
]